mycloud/__init__.py
mycloud/__main__.py
mycloud/inject.py
mycloud/logger.py
mycloud/commands/__init__.py
mycloud/commands/auth.py
mycloud/commands/shared.py
mycloud/commands/statistics.py
mycloud/commands/drive/__init__.py
mycloud/commands/drive/convert.py
mycloud/commands/drive/delete.py
mycloud/commands/drive/download.py
mycloud/commands/drive/upload.py
mycloud/common/__init__.py
mycloud/common/directory_list.py
mycloud/common/functions.py
mycloud/common/operation_timeout.py
mycloud/common/sha256_file.py
mycloud/constants/__init__.py
mycloud/credentials/__init__.py
mycloud/credentials/storage.py
mycloud/filesync/__init__.py
mycloud/filesync/downsync.py
mycloud/filesync/remote_file_conversion.py
mycloud/filesync/tree.py
mycloud/filesync/upsync.py
mycloud/filesync/progress/__init__.py
mycloud/filesync/progress/progress_tracker.py
mycloud/filesystem/__init__.py
mycloud/filesystem/file_manager.py
mycloud/filesystem/file_metadata.py
mycloud/filesystem/file_version.py
mycloud/filesystem/metadata_manager.py
mycloud/filesystem/translatable_path.py
mycloud/filesystem/versioned_stream_accessor.py
mycloud/mycloudapi/__init__.py
mycloud/mycloudapi/helper.py
mycloud/mycloudapi/object_resource_builder.py
mycloud/mycloudapi/request_executor.py
mycloud/mycloudapi/response.py
mycloud/mycloudapi/auth/__init__.py
mycloud/mycloudapi/auth/bearer_token.py
mycloud/mycloudapi/auth/mycloud_authenticator.py
mycloud/mycloudapi/auth/selenium_proxy.py
mycloud/mycloudapi/auth/undetectable-headless-browser.js
mycloud/mycloudapi/requests/__init__.py
mycloud/mycloudapi/requests/request.py
mycloud/mycloudapi/requests/drive/__init__.py
mycloud/mycloudapi/requests/drive/change_request.py
mycloud/mycloudapi/requests/drive/directory_list_request.py
mycloud/mycloudapi/requests/drive/metadata_request.py
mycloud/mycloudapi/requests/drive/object_request.py
mycloud/mycloudapi/requests/drive/rename_request.py
mycloud/mycloudapi/requests/drive/usage_request.py
mycloud/statistics/__init__.py
mycloud_cli-1.2.3.dist-info/LICENSE
mycloud_cli-1.2.3.dist-info/METADATA
mycloud_cli-1.2.3.dist-info/WHEEL
mycloud_cli-1.2.3.dist-info/entry_points.txt
mycloud_cli-1.2.3.dist-info/top_level.txt
mycloud_cli-1.2.3.dist-info/RECORD
